debug_dojo/__init__.py
debug_dojo/__main__.py
debug_dojo/_cli.py
debug_dojo/_compare.py
debug_dojo/_config.py
debug_dojo/_config_models.py
debug_dojo/_installers.py
debug_dojo/install.py
debug_dojo/py.typed
debug_dojo-0.5.0.dist-info/licenses/LICENSE
debug_dojo-0.5.0.dist-info/METADATA
debug_dojo-0.5.0.dist-info/WHEEL
debug_dojo-0.5.0.dist-info/entry_points.txt
debug_dojo-0.5.0.dist-info/top_level.txt
debug_dojo-0.5.0.dist-info/RECORD
