Metadata-Version: 2.4
Name: debug-dojo
Version: 0.5.0
Summary: 🏣 debug dojo, a place for zen debugging
Author-email: bwrob <bartosz.marcin.wroblewski@gmail.com>
License-Expression: MIT
Project-URL: Changelog, https://bwrob.github.io/debug-dojo/changelog/
Project-URL: Documentation, https://bwrob.github.io/debug-dojo/
Project-URL: Homepage, https://bwrob.github.io/debug-dojo/
Project-URL: Source, https://github.com/bwrob/debug-dojo/
Keywords: debugging,inspection,tools,development
Classifier: Intended Audience :: Developers
Classifier: Operating System :: OS Independent
Classifier: Programming Language :: Python :: 3.10
Classifier: Programming Language :: Python :: 3.11
Classifier: Programming Language :: Python :: 3.12
Classifier: Programming Language :: Python :: 3.13
Classifier: Topic :: Software Development :: Debuggers
Classifier: Topic :: Software Development :: Libraries :: Python Modules
Requires-Python: <3.14,>=3.10
License-File: LICENSE
Requires-Dist: debugpy>=1.8.0
Requires-Dist: ipdb>=0.13.0
Requires-Dist: pudb>=2020.1
Requires-Dist: pydantic>=2.11.7
Requires-Dist: rich>=12.0.0
Requires-Dist: tomlkit>=0.13.3
Requires-Dist: typer>=0.15.0
Dynamic: license-file
